setup.py
crypto_mediator/__init__.py
crypto_mediator/example.py
crypto_mediator/settings.py
crypto_mediator/testing.py
crypto_mediator.egg-info/PKG-INFO
crypto_mediator.egg-info/SOURCES.txt
crypto_mediator.egg-info/dependency_links.txt
crypto_mediator.egg-info/requires.txt
crypto_mediator.egg-info/top_level.txt
crypto_mediator/clients/__init__.py
crypto_mediator/clients/client.py
crypto_mediator/clients/helpers.py
crypto_mediator/clients/tests/__init__.py
crypto_mediator/clients/tests/test_client.py
crypto_mediator/clients/tests/test_helpers.py
crypto_mediator/fixtures/__init__.py